ARR_tool/__init__.py
ARR_tool/generate_prediction.py
ARR_tool/modelTraining.py
ARR_tool/outlook.py
ARR_tool/updateTable.py
arr_tool-0.0.4.dist-info/METADATA
arr_tool-0.0.4.dist-info/WHEEL
arr_tool-0.0.4.dist-info/licenses/LICENSE
arr_tool-0.0.4.dist-info/RECORD
