Metadata-Version: 2.3
Name: ARR_tool
Version: 0.0.4
Summary: A tool for making prediction
Author: DAA
License-File: LICENSE
Classifier: Operating System :: OS Independent
Classifier: Programming Language :: Python :: 3
Requires-Python: >=3.11
